stone_connect/__init__.py
stone_connect/client.py
stone_connect/exceptions.py
stone_connect/models.py
stone_connect/py.typed
stone_connect-0.1.1.dist-info/METADATA
stone_connect-0.1.1.dist-info/WHEEL
stone_connect-0.1.1.dist-info/entry_points.txt
stone_connect-0.1.1.dist-info/licenses/LICENSE
stone_connect-0.1.1.dist-info/RECORD
