Metadata-Version: 2.4
Name: stone-connect
Version: 0.1.1
Summary: Async Python library for controlling Stone Connect WiFi electric heaters
Project-URL: Homepage, https://github.com/tomasbedrich/stone-connect
Project-URL: Documentation, https://github.com/tomasbedrich/stone-connect#readme
Project-URL: Repository, https://github.com/tomasbedrich/stone-connect.git
Project-URL: Issues, https://github.com/tomasbedrich/stone-connect/issues
Author-email: Tomas Bedrich <ja@tbedrich.cz>
License: MIT
License-File: LICENSE
Keywords: automation,connect,heater,home,smart,stone,wifi
Classifier: Development Status :: 4 - Beta
Classifier: Intended Audience :: Developers
Classifier: License :: OSI Approved :: MIT License
Classifier: Operating System :: OS Independent
Classifier: Programming Language :: Python :: 3
Classifier: Programming Language :: Python :: 3.8
Classifier: Programming Language :: Python :: 3.9
Classifier: Programming Language :: Python :: 3.10
Classifier: Programming Language :: Python :: 3.11
Classifier: Programming Language :: Python :: 3.12
Classifier: Programming Language :: Python :: 3.13
Classifier: Topic :: Home Automation
Classifier: Topic :: Software Development :: Libraries :: Python Modules
Requires-Python: >=3.8
Requires-Dist: aiohttp>=3.8.0
Provides-Extra: dev
Requires-Dist: mypy>=1.0.0; extra == 'dev'
Requires-Dist: pytest-asyncio>=0.21.0; extra == 'dev'
Requires-Dist: pytest-cov>=4.0.0; extra == 'dev'
Requires-Dist: pytest>=7.0.0; extra == 'dev'
Requires-Dist: ruff>=0.1.0; extra == 'dev'
Provides-Extra: examples
Requires-Dist: asyncio; extra == 'examples'
